dlb_launcher.py
dlb/__init__.py
dlb/version.py
dlb/cf/__init__.py
dlb/cf/level.py
dlb/di/__init__.py
dlb/ex/__init__.py
dlb/ex/_aseq.py
dlb/ex/_context.py
dlb/ex/_depend.py
dlb/ex/_dependaction.py
dlb/ex/_error.py
dlb/ex/_mult.py
dlb/ex/_platform.py
dlb/ex/_rundb.py
dlb/ex/_tool.py
dlb/ex/_toolrun.py
dlb/ex/_worktree.py
dlb/ex/input.py
dlb/ex/output.py
dlb/fs/__init__.py
dlb/ut/__init__.py
dlb_contrib/backslashescape.py
dlb_contrib/clike.py
dlb_contrib/doxygen.py
dlb_contrib/doxypress.py
dlb_contrib/exctrace.py
dlb_contrib/exportenv.py
dlb_contrib/filesystem.py
dlb_contrib/gcc.py
dlb_contrib/generic.py
dlb_contrib/git.py
dlb_contrib/gnubinutils.py
dlb_contrib/gnumake.py
dlb_contrib/iso6429.py
dlb_contrib/linux.py
dlb_contrib/msbatch.py
dlb_contrib/mscrt.py
dlb_contrib/msvc.py
dlb_contrib/partition.py
dlb_contrib/pkgconfig.py
dlb_contrib/python.py
dlb_contrib/sh.py
dlb_contrib/strace.py
dlb_contrib/tex.py
dlb_contrib/url.py
dlb_contrib/versioned_interface.py
dlb_contrib/zip.py
dlb-0.6.1.dist-info/COPYING
dlb-0.6.1.dist-info/COPYING.LESSER
dlb-0.6.1.dist-info/METADATA
dlb-0.6.1.dist-info/WHEEL
dlb-0.6.1.dist-info/entry_points.txt
dlb-0.6.1.dist-info/top_level.txt
dlb-0.6.1.dist-info/zip-safe
dlb-0.6.1.dist-info/RECORD
